.coverage
.gitattributes
.gitignore
.travis.yml
CITATION.bib
CODE_OF_CONDUCT.md
LICENSE
README.md
README.rst
clx_unittest.py
coverage.xml
precompile.sh
record.txt
requirements.txt
runtest.py
setup.py
.github/workflows/codecov.yml
.github/workflows/package_release.yml
.vscode/settings.json
classix/__init__.py
classix/aggregation.py
classix/aggregation_c.c
classix/aggregation_c.pyx
classix/aggregation_cm.c
classix/aggregation_cm.pyx
classix/aggregation_test.py
classix/clustering.py
classix/merging.py
classix/merging_cm.c
classix/merging_cm.pyx
classix/__pycache__/__init__.cpython-39.pyc
classix/__pycache__/aggregation.cpython-39.pyc
classix/__pycache__/aggregation_test.cpython-39.pyc
classix/__pycache__/clustering.cpython-39.pyc
classix/__pycache__/merging.cpython-39.pyc
classix/data/checkpoint_density_0.5.npy
classix/data/checkpoint_density_0.6.npy
classix/data/checkpoint_density_0.7.npy
classix/data/checkpoint_density_0.8.npy
classix/data/checkpoint_density_0.9.npy
classix/data/checkpoint_density_1.0.npy
classix/data/checkpoint_distance_0.5.npy
classix/data/checkpoint_distance_0.6.npy
classix/data/checkpoint_distance_0.7.npy
classix/data/checkpoint_distance_0.8.npy
classix/data/checkpoint_distance_0.9.npy
classix/data/checkpoint_distance_1.0.npy
classix/source/X_Banknote.npy
classix/source/X_Dermatology.npy
classix/source/X_Ecoli.npy
classix/source/X_Glass.npy
classix/source/X_Irirs.npy
classix/source/X_Phoneme.npy
classix/source/X_Seeds.npy
classix/source/X_Wine.npy
classix/source/vdu_signals.npy
classix/source/y_Banknote.npy
classix/source/y_Dermatology.npy
classix/source/y_Ecoli.npy
classix/source/y_Glass.npy
classix/source/y_Irirs.npy
classix/source/y_Phoneme.npy
classix/source/y_Seeds.npy
classix/source/y_Wine.npy
classixclustering.egg-info/PKG-INFO
classixclustering.egg-info/SOURCES.txt
classixclustering.egg-info/dependency_links.txt
classixclustering.egg-info/requires.txt
classixclustering.egg-info/top_level.txt