Metadata-Version: 2.1
Name: classixclustering
Version: 0.7.1
Summary: Fast and explainable clustering based on sorting
Home-page: https://github.com/nla-group/CLASSIX.git
Author: Xinye Chen, Stefan Güttel
Author-email: xinye.chen@manchester.ac.uk, stefan.guettel@manchester.ac.uk
License: MIT License
Platform: UNKNOWN
Classifier: Intended Audience :: Science/Research
Classifier: Intended Audience :: Developers
Classifier: Programming Language :: Python
Classifier: Topic :: Software Development
Classifier: Topic :: Scientific/Engineering
Classifier: Operating System :: Microsoft :: Windows
Classifier: Operating System :: POSIX
Classifier: Operating System :: Unix
Classifier: Operating System :: MacOS
Classifier: Programming Language :: Python :: 3
Classifier: Programming Language :: Python :: 3.6
Classifier: Programming Language :: Python :: 3.7
Classifier: Programming Language :: Python :: 3.8
Classifier: Programming Language :: Python :: 3.9
Classifier: Programming Language :: Python :: 3.10
License-File: LICENSE
